aws_ecs_service/__init__.py
aws_ecs_service/ecs_service.py
aws_ecs_service/package/__init__.py
aws_ecs_service/package/action.py
aws_ecs_service/package/cfnresponse.py
aws_ecs_service/package/fix_kwargs.py
aws_ecs_service/package/index.py
aws_ecs_service/package/response.py
aws_ecs_service-1.3.0.dist-info/LICENSE
aws_ecs_service-1.3.0.dist-info/METADATA
aws_ecs_service-1.3.0.dist-info/WHEEL
aws_ecs_service-1.3.0.dist-info/top_level.txt
aws_ecs_service-1.3.0.dist-info/RECORD
