Metadata-Version: 2.1
Name: aws-ecs-service
Version: 1.3.0
Summary: AWS CDK package that manages ecs service resource.
Home-page: https://github.com/idenfy/AwsEcsService.git
Author: Laimonas Sutkus
Author-email: laimonas@idenfy.com, laimonas.sutkus@gmail.com
License: GNU GENERAL PUBLIC LICENSE Version 3
Keywords: AWS CDK ECS CustomResource
Platform: UNKNOWN
Classifier: Programming Language :: Python :: 3.6
Classifier: Programming Language :: Python :: 3.7
Classifier: Programming Language :: Python :: 3.8
Classifier: Operating System :: OS Independent
Requires-Dist: aws-cdk.core (<2.0.0,>=1.60.0)
Requires-Dist: aws-cdk.custom-resources (<2.0.0,>=1.60.0)
Requires-Dist: aws-cdk.aws-lambda (<2.0.0,>=1.60.0)
Requires-Dist: aws-cdk.aws-iam (<2.0.0,>=1.60.0)
